TgrEzLi/__init__.py
TgrEzLi/core.py
tgrezli-0.1.2.dist-info/METADATA
tgrezli-0.1.2.dist-info/WHEEL
tgrezli-0.1.2.dist-info/top_level.txt
tgrezli-0.1.2.dist-info/RECORD
