Metadata-Version: 2.2
Name: TgrEzLi
Version: 0.1.2
Summary: Easy-to-use synchronous interface for telegram-bot library with async backend and intuitive handlers.
Home-page: https://github.com/eaannist/TgrEzLi
Author: eaannist
Author-email: eaannist@gmail.com
Classifier: Programming Language :: Python :: 3
Classifier: Operating System :: OS Independent
Requires-Python: >=3.7
Requires-Dist: python-telegram-bot>=20.0
Requires-Dist: requests>=2.28.0
Requires-Dist: PyCypherLib>=1.3.5
Dynamic: author
Dynamic: author-email
Dynamic: classifier
Dynamic: description
Dynamic: description-content-type
Dynamic: home-page
Dynamic: requires-dist
Dynamic: requires-python
Dynamic: summary
